{
  "flanking": {
    "enabled": false,
    "meleeOrgDamageModifier": 0,
    "rearMeleeOrgDamageModifier": 0,
    "chargePenetrationModifier": 0,
    "rearChargePenetrationModifier": 0
  },
  "stamina": {
    "enabled": false,
    "meleeTurnCost": 0,
    "rangedTurnCost": 0,
    "hasRanMeleeStaminaCostModifier": 0,
    "regainRates": {
      "range1": 0,
      "range2": 0,
      "range3": 0,
      "range4": 0,
      "range5": 0
    },
    "upperModifierLimit": 0,
    "lowerModifierLimit": 0,
    "chargeResistanceModifier": 0,
    "runningMovementPenalty": 0,
    "rangedAttackPenalty": 0,
    "meleeAttackPenalty": 0,
    "meleeDefensePenalty": 0
  },
  "ammo": {
    "enabled": false,
    "baseReserve": 500,
    "regenerationBaseRate": 0.04,
    "regenerationBonusRate": 0.07,
    "maxHpConsumptionReduction": -0.6
  }
}
