{
  "blitz": {
    "manpower": 1950,
    "gold": 1050,
    "skirmisherRatio": [0, 1],
    "fogOfWar": false,
    "unitCaps": {
      "17": 0,
      "19": 2
    }
  },
  "encounter": {
    "manpower": 4250,
    "gold": 2500,
    "skirmisherRatio": [1, 2],
    "fogOfWar": false,
    "unitCaps": {
      "17": 3,
      "19": 1
    }
  },
  "battle": {
    "manpower": 7300,
    "gold": 4250,
    "skirmisherRatio": [3, 6],
    "fogOfWar": true,
    "unitCaps": {
      "17": 6,
      "19": 2
    }
  },
  "grand_battle": {
    "manpower": 14600,
    "gold": 8500,
    "skirmisherRatio": [2, 5],
    "fogOfWar": true,
    "unitCaps": {
      "17": 8,
      "19": 2
    }
  }
}
